qoverage/__init__.py
qoverage/__main__.py
qoverage/annotate.py
qoverage/dom.py
qoverage/find_qmldom.py
qoverage/parse_coverage.py
qoverage/qmldom.py
qoverage/report.py
qoverage/bundled_qmldom/qmldom
qoverage/qml_import/QoverageSingleton/QoverageSingleton.qml
qoverage/qml_import/QoverageSingleton/qmldir
qoverage/templates/file_tracker.template.js
qoverage-0.1.13.dist-info/LICENSE
qoverage-0.1.13.dist-info/METADATA
qoverage-0.1.13.dist-info/WHEEL
qoverage-0.1.13.dist-info/entry_points.txt
qoverage-0.1.13.dist-info/top_level.txt
qoverage-0.1.13.dist-info/RECORD
