Metadata-Version: 2.1
Name: qoverage
Version: 0.1.13
Summary: Code coverage for QML
Author-email: Sander Vocke <sandervocke@gmail.com>
Maintainer-email: Sander Vocke <sandervocke@gmail.com>
License: GNU GENERAL PUBLIC LICENSE
Project-URL: Homepage, https://github.com/SanderVocke/qoverage
Project-URL: Bug Tracker, https://github.com/SanderVocke/qoverage/issues
Project-URL: Discussions, https://github.com/SanderVocke/qoverage/discussions
Keywords: qml,coverage
Classifier: Development Status :: 2 - Pre-Alpha
Classifier: License :: OSI Approved :: GNU Lesser General Public License v2 or later (LGPLv2+)
Classifier: Programming Language :: Python :: 3 :: Only
Classifier: Programming Language :: Python :: 3.7
Classifier: Programming Language :: Python :: 3.8
Classifier: Programming Language :: Python :: 3.9
Classifier: Programming Language :: Python :: 3.10
Classifier: Programming Language :: Python :: 3.11
Classifier: Operating System :: POSIX :: Linux
Classifier: Programming Language :: Other
Requires-Python: >=3.7
License-File: LICENSE
Provides-Extra: test
Requires-Dist: pytest ; extra == 'test'
